iobeam/__init__.py
iobeam/iobeam.py
iobeam/endpoints/__init__.py
iobeam/endpoints/devices.py
iobeam/endpoints/exports.py
iobeam/endpoints/imports.py
iobeam/endpoints/service.py
iobeam/endpoints/tokens.py
iobeam/http/__init__.py
iobeam/http/request.py
iobeam/resources/__init__.py
iobeam/resources/data.py
iobeam/resources/device.py
iobeam/resources/query.py
iobeam/utils/__init__.py
iobeam/utils/utils.py
iobeam-0.11.0.dist-info/DESCRIPTION.rst
iobeam-0.11.0.dist-info/METADATA
iobeam-0.11.0.dist-info/RECORD
iobeam-0.11.0.dist-info/WHEEL
iobeam-0.11.0.dist-info/metadata.json
iobeam-0.11.0.dist-info/top_level.txt
