Metadata-Version: 2.0
Name: iobeam
Version: 0.11.0
Summary: Library for connecting to iobeam, the data analysis     platform for the Internet of Things (IoT).
Home-page: https://github.com/iobeam/iobeam-client-python
Author: iobeam
Author-email: support@iobeam.com
License: Apache Software License
Keywords: iot data analytics iobeam sensors
Platform: UNKNOWN
Classifier: Development Status :: 4 - Beta
Classifier: Intended Audience :: Developers
Classifier: Topic :: Software Development :: Build Tools
Classifier: License :: OSI Approved :: Apache Software License
Classifier: Programming Language :: Python
Classifier: Programming Language :: Python :: 2.7
Classifier: Programming Language :: Python :: 3.4
Classifier: Programming Language :: Python :: 3.5
Requires-Dist: pyjwt
Requires-Dist: requests
